{
  "BlobStorageContainerName": "project-files-playa",
  "acApp": "AC",
  "accountCompanyId": "18",
  "azureStorage": true,
  "canSendAlert": "false",
  "cdn": "https://newgiza.azureedge.net",
  "chatLocal": "https://playa.procoor.com",
  "chatStatic": "https://playa.procoor.com",
  "exportLocal": "https://playa.procoor.com",
  "exportStatic": "https://playa.procoor.com",
  "fmApp": "FM",
  "hrApp": "HR",
  "local": "https://playaServices.procoor.com/",
  "loginServer": "https://procoorauthorization.procoor.com",
  "pmApp": "PM",
  "static": "https://playaServices.procoor.com/",
  "downloads": "https://playaServices.procoor.com",
  "dropBoxappKey": "r8iiezlpm1pvlry",
  "dropBoxToken": "H_FU-3QESeAAAAAAAAABXQHST0VO0rFTX4tYhzru1_J9AFywzjAwxrv4wQgTJDbN",
  "googleDriveClientId": "850532811390-1tqkrqcgjghv9tis79l92avsv03on7nf.apps.googleusercontent.com",
  "googleDriveKey": "uof5qzvtwpq1dao",
  "refAutomatic": false,
  "exportCore": "https://playaServices.procoor.com/ExportAPI/api/ExportController/",
  "client_id": "5igADs8UAtwBCf154WI088jfvNKx8zGI",
  "client_secret": "1u0aV9Ue8lkMPAZT",
  "commonLogApi": 2,
  "dashboardApi": 1,
  "refCodeValidation": false,
  "activeExport": true,
  "useBackResources": false
}