{   "22": {
    "fields": [
        {
            "name":"fromCompany",
            "value":"fromCompanyName",
            "type":"S"
        },
        {
        "name":"refDoc",
        "value":"refDoc",
        "type":"S"
        },
       {
        "name": "description",
        "value": "description",
        "type": "S"
       },
        {
            "name": "subject",
            "value": "subject",
            "type": "S"
        },
        {
            "name": "numberAbb",
            "value": "arrange",
            "type": "S"
        },
        {
            "name": "docDate",
            "value": "docDate",
            "type": "D"
        },
        {
            "name": "status",
            "value": "statusName",
            "type": "S"
        },
        {
            "name": "fromContact",
            "value": "fromContactName",
            "type": "S"
        },
        {
            "name": "toCompany",
            "value": "toCompanyName",
            "type": "S"
        },
        {
            "name": "attention",
            "value": "toContactName",
            "type": "S"
        },
        {
            "name": "projectName",
            "value": "projectName",
            "type": "S"
        }
    ],
    "columnsItems": [

        
    ],
    "friendlyNames": [

    ]
},

    "10": {
        "fields": [
            {
                "name": "subject",
                "value": "subject",
                "type": "S"
            },
            {
                "name": "numberAbb",
                "value": "arrange",
                "type": "S"
            },
            {
                "name": "docDate",
                "value": "docDate",
                "type": "D"
            },
            {
                "name": "status",
                "value": "statusName",
                "type": "S"
            }
        ],
        "columnsItems": [
            "arrange",
            "description",
            "bicContactName",
            "bicCompanyName",
            "startDate",
            "finishDate",
            "taskId"
        ],
        "friendlyNames": [
            "number",
            "description",
            "ToContact",
            "toCompany",
            "startDate",
            "finishDate",
            "activityId"
        ]
    },
    "13": {
        "fields": [
            {
                "name": "subject",
                "value": "subject",
                "type": "S"
            },
            {
                "name": "docDate",
                "value": "docDate",
                "type": "D"
            },
            {
                "name": "status",
                "value": "statusName",
                "type": "S"
            },
            {
                "name": "alertStatus",
                "value": "alertStatusName",
                "type": "S"
            }
        ],
        "columnsItems": [
            "arrange",
            "task_id",
            "task_code",
            "description",
            "early_start_date",
            "early_end_date",
            "start_date",
            "finish_date"
        ],
        "friendlyNames": [
            "numberAbb",
            "taskId",
            "taskCode",
            "activityDescription",
            "earlyStartDate",
            "earlyEndDate",
            "lateStartDate",
            "lateEndDate"
        ]
    },
    "19": {
        "fields": [
            {
                "showInMainFields": true,
                "isConact": true,
                "name": "attention",
                "fields": [
                    {
                        "value": "toCompanyName",
                        "type": "S"
                    },
                    {
                        "value": "toContactName",
                        "type": "S"
                    }
                ]
            },
            {
                "showInMainFields": true,
                "isConact": true,
                "name": "fromContact",
                "fields": [
                    {
                        "value": "fromCompanyName",
                        "type": "S"
                    },
                    {
                        "value": "fromContactName",
                        "type": "S"
                    }
                ]
            },
            {
                "isConact": false,
                "showInMainFields": true,
                "name": "docDate",
                "value": "docDate",
                "type": "D"
            },
            {
                "isConact": false,
                "showInMainFields": true,
                "name": "subject",
                "value": "subject",
                "type": "S"
            },
            {
                "isConact": false,
                "showInMainFields": true,
                "name": "status",
                "value": "statusName",
                "type": "S"
            },
            {
                "isConact": false,
                "showInMainFields": false,
                "name": "refDoc",
                "value": "refDoc",
                "type": "S"
            },
            {
                "isConact": false,
                "showInMainFields": true,
                "name": "projectName",
                "value": "projectName",
                "type": "S"
            },
            {
                "isConact": false,
                "showInMainFields": true,
                "name": "numberAbb",
                "value": "arrange",
                "type": "S"
            },
            {
                "isConact": false,
                "showInMainFields": false,
                "name": "message",
                "value": "message ",
                "type": "S"
            }
        ],
        "columnsItems": [],
        "friendlyNames": []
    },
    "28": {
        "fields": [
            {
                "name": "subject",
                "value": "subject",
                "type": "S"
            },
            {
                "name": "status",
                "value": "statusName",
                "type": "S"
            },
            {
                "name": "refDoc",
                "value": "refDoc",
                "type": "S"
            },
            {
                "name": "docDate",
                "value": "docDate",
                "type": "D"
            },
            {
                "name": "requiredDate",
                "value": "requiredDate",
                "type": "D"
            },
            {
                "name": "sendingMethod",
                "value": "sendingMethodName",
                "type": "S"
            },
            {
                "name": "submittedFor",
                "value": "submittedForName",
                "type": "S"
            },
            {
                "name": "description",
                "value": "description",
                "type": "S"
            },
            {
                "name": "discipline",
                "value": "discipline",
                "type": "S"
            },
            {
                "name": "area",
                "value": "area ",
                "type": "S"
            },
            {
                "name": "buildingNumber",
                "value": "building",
                "type": "S"
            },
            {
                "name": "apartmentNumber",
                "value": "apartment",
                "type": "S"
            },
            {
                "name": "fromCompany",
                "value": "fromCompanyName",
                "type": "S"
            },
            {
                "name": "fromContact",
                "value": "fromContactName",
                "type": "S"
            },
            {
                "name": "toCompany",
                "value": "toCompanyName",
                "type": "S"
            },
            {
                "name": "attention",
                "value": "toContactName",
                "type": "S"
            },
            {
                "name": "projectName",
                "value": "projectName",
                "type": "S"
            }
        ],
        "columnsItems": [],
        "friendlyNames": []
    },
    "25": {
        "fields": [
            {
                "name": "subject",
                "value": "subject",
                "type": "S"
            },
            {
                "name": "projectName",
                "value": "projectName",
                "type": "S"
            },
            {
                "name": "status",
                "value": "statusName",
                "type": "S"
            },
            {
                "name": "docDate",
                "value": "docDate",
                "type": "D"
            },
            {
                "name": "arrange",
                "value": "arrange",
                "type": "S"
            },
            {
                "name": "refrences",
                "value": "refDoc",
                "type": "S"
            },
            {
                "name": "requiredDate",
                "value": "requiredDate",
                "type": "D"
            },
            {
                "name": "fromCompany",
                "value": "fromCompanyName",
                "type": "S"
            },
            {
                "name": "fromContact",
                "value": "fromContactName",
                "type": "S"
            },
            {
                "name": "toCompany",
                "value": "toCompanyName",
                "type": "S"
            },
            {
                "name": "ToContact",
                "value": "toContactName",
                "type": "S"
            },
            {
                "name": "actionByCompany",
                "value": "bicCompanyName",
                "type": "S"
            },
            {
                "name": "actionByContact",
                "value": "bicContactName",
                "type": "S"
            },
            {
                "name": "contractPo",
                "value": "orderSubject",
                "type": "S"
            },
            {
                "name": "discipline",
                "value": "disciplineName",
                "type": "S"
            },
            {
                "name": "specsSection",
                "value": "specsSectionName",
                "type": "S"
            },
            {
                "name": "reasonForIssue",
                "value": "reasonForIssueName",
                "type": "S"
            },
            {
                "name": "fileNumber",
                "value": "fileNumberName",
                "type": "S"
            },
            {
                "name": "area",
                "value": "areaName",
                "type": "S"
            },
            {
                "name": "Building",
                "value": "buildingNoName",
                "type": "S"
            },
            {
                "name": "apartmentNumber",
                "value": "apartmentNoName",
                "type": "S"
            },
            {
                "name": "message",
                "value": "rfi",
                "type": "S"
            },
            {
                "name": "CycleDetails",
                "value": " ",
                "type": "L"
            },
            {
                "name": "cycleDate",
                "value": "cycleDocDate",
                "type": "D"
            },
            {
                "name": "resultDate",
                "value": "resultDate",
                "type": "D"
            }
        ],
        "columnsItems": [
            "arrange",
            "subject",
            "statusName",
            "flowCompanyName",
            "flowContactName",
            "docDate",
            "approvalStatusName",
            "progressPercent",
            "cycleComment"
        ],
        "friendlyNames": [
            "numberAbb",
            "subject",
            "status",
            "CompanyName",
            "ContactName",
            "docDate",
            "approvalStatus",
            "progressPercent",
            "answer"
        ]
    },
    "51": {
        "fields": [
            {
                "name": "subject",
                "value": "subject",
                "type": "S"
            },
            {
                "name": "status",
                "value": "statusName",
                "type": "S"
            },
            {
                "name": "docDate",
                "value": "docDate",
                "type": "D"
            },
            {
                "name": "specsSection",
                "value": "specsSectionName",
                "type": "S"
            },
            {
                "name": "fromCompany",
                "value": "orderFromCompanyName",
                "type": "S"
            },
            {
                "name": "orderFromContact",
                "value": "orderFromContactName",
                "type": "S"
            },
            {
                "name": "siteRequest",
                "value": "siteRequestName",
                "type": "S"
            },
            {
                "name": "materialReleaseType",
                "value": "materialReleaseName",
                "type": "S"
            },
            {
                "name":"boqLog",
                "value":"boqName",
                "type":"S"
            }
        ],
        "columnsItems": [
            "arrange",
            "description",
            "quantity",
            "unitPrice",
            "resourceCode",
            "areaName",
            "locationName",
            "remarks"
        ],
        "friendlyNames": [
            "arrange",
            "description",
            "quantity",
            "unitPrice",
            "resourceCode",
            "area",
            "location",
            "remarks"
        ]
    },
    "50": {
        "fields": [
            {
                "name": "description",
                "value": "description",
                "type": "S"
            },
            {
                "name": "arrange",
                "value": "arrange",
                "type": "S"
            },
            {
                "name": "unit",
                "value": "unit",
                "type": "S"
            },
            {
                "name": "resourceCode",
                "value": "resourceCode",
                "type": "S"
            },
            {
                "name": "disciplineName",
                "value": "disciplineName",
                "type": "S"
            },
            {
                "name": "specsSection",
                "value": "specsSectionName",
                "type": "S"
            },
            {
                "name": "remainingQuantity",
                "value": "remainingQuantity",
                "type": "S"
            },
            {
                "name": "unitPrice",
                "value": "unitPrice",
                "type": "S"
            }
        ],
        "columnsItems": [],
        "friendlyNames": []
    },
    "109": {
        "fields": [
            {
                "name": "subject",
                "value": "subject",
                "type": "S"
            },
            {
                "name": "numberAbb",
                "value": "arrange",
                "type": "S"
            },
            {
                "name": "status",
                "value": "statusName",
                "type": "S"
            },
            {
                "name": "docDate",
                "value": "docDate",
                "type": "D"
            },
            {
                "name": "refDoc",
                "value": "refDoc",
                "type": "S"
            },
            {
                "name": "fromCompany",
                "value": "fromCompanyName",
                "type": "S"
            },
            {
                "name": "fromContact",
                "value": "fromContactName",
                "type": "S"
            },
            {
                "name": "toCompany",
                "value": "toCompanyName",
                "type": "S"
            },
            {
                "name": "attention",
                "value": "toContactName",
                "type": "S"
            },
            {
                "name": "projectName",
                "value": "projectName ",
                "type": "S"
            }
        ],
        "columnsItems": [],
        "friendlyNames": []
    },
    "61": {
        "fields": [
            {
                "name": "subject",
                "value": "subject",
                "type": "S"
            },
            {
                "name": "docDate",
                "value": "docDate",
                "type": "D"
            },
            {
                "name": "fromCompany",
                "value": "fromCompanyName",
                "type": "S"
            },
            {
                "name": "actionByCompany",
                "value": "bicCompanyName",
                "type": "S"
            },
            {
                "name": "contractPo",
                "value": "orderType",
                "type": "S"
            },
            {
                "name": "projectName",
                "value": "projectName",
                "type": "S"
            },
            {
                "name": "status",
                "value": "statusName",
                "type": "S"
            },
            {
                "name": "discipline",
                "value": "disciplineName",
                "type": "S"
            },
            {
                "name": "toCompany",
                "value": "toCompanyName",
                "type": "S"
            },
            {
                "name": "actionByContact",
                "value": "bicContactName",
                "type": "S"
            },
            {
                "name": "area",
                "value": "areaName",
                "type": "S"
            }
        ],
        "columnsItems": [
            "arrange",
            "description",
            "bicCompanyName",
            "bicContactName",
            "areaName",
            "locationName",
            "openedDate",
            "requiredDate"
        ],
        "friendlyNames": [
            "numberAbb",
            "description",
            "actionByCompany",
            "actionByContact",
            "area",
            "location",
            "openedDate",
            "requiredDateLog"
        ]
    },
    "101": {
        "fields": [
            {
                "name": "subject",
                "value": "subject",
                "type": "S"
            },
            {
                "name": "status",
                "value": "statusName",
                "type": "S"
            },
            {
                "name": "docDate",
                "value": "docDate",
                "type": "D"
            },
            {
                "name": "reviewResult",
                "value": "reviewResultName",
                "type": "S"
            },
            {
                "name": "inspectionRequest",
                "value": "inspectionRequestName",
                "type": "S"
            },
            {
                "name": "fileNumber",
                "value": "fileNumberName",
                "type": "S"
            },
            {
                "name": "Building",
                "value": "buildingNoName",
                "type": "S"
            },
            {
                "name": "fromCompany",
                "value": "fromCompanyName",
                "type": "S"
            },
            {
                "name": "toCompany",
                "value": "toCompanyName",
                "type": "S"
            },
            {
                "name": "projectName",
                "value": "projectName",
                "type": "S"
            },
            {
                "name": "numberAbb",
                "value": "arrange",
                "type": "S"
            },
            {
                "name": "refNo",
                "value": "refDoc",
                "type": "S"
            },
            {
                "name": "requiredDate",
                "value": "requiredDate",
                "type": "D"
            },
            {
                "name": "specsSection",
                "value": "specsSectionName",
                "type": "S"
            },
            {
                "name": "discipline",
                "value": "discipline",
                "type": "S"
            },
            {
                "name": "area",
                "value": "areaName",
                "type": "S"
            },
            {
                "name": "apartmentNumber",
                "value": "apartmentNoName",
                "type": "S"
            },
            {
                "name": "fromContact",
                "value": "fromContactName",
                "type": "S"
            },
            {
                "name": "attention",
                "value": "toContactName",
                "type": "S"
            }
        ],
        "columnsItems": [],
        "friendlyNames": []
    },
    "30": {
        "fields": [
            {
                "name": "subject",
                "value": "subject",
                "type": "S"
            },
            {
                "name": "status",
                "value": "statusName",
                "type": "S"
            },
            {
                "name": "docDate",
                "value": "docDate",
                "type": "D"
            },
            {
                "name": "requiredDate",
                "value": "requiredDate",
                "type": "D"
            },
            {
                "name": "numberAbb",
                "value": "arrange",
                "type": "S"
            },
            {
                "name": "refDoc",
                "value": "refDoc",
                "type": "S"
            },
            {
                "name": "fromCompany",
                "value": "fromCompanyName",
                "type": "S"
            },
            {
                "name": "fromContact",
                "value": "fromContactName",
                "type": "S"
            },
            {
                "name": "toCompanyName",
                "value": "toCompanyName",
                "type": "S"
            },
            {
                "name": "toContactName",
                "value": "toContactName",
                "type": "S"
            },
            {
                "name": "projectName",
                "value": "projectName",
                "type": "S"
            }
        ],
        "columnsItems": [],
        "friendlyNames": []
    },
    "35": {
        "fields": [
            {
                "name": "subject",
                "value": "subject",
                "type": "S"
            },
            {
                "name": "handouts",
                "value": "handOuts",
                "type": "S"
            },
            {
                "name": "status",
                "value": "statusName",
                "type": "S"
            },
            {
                "name": "refDoc",
                "value": "refDoc",
                "type": "S"
            },
            {
                "name": "docDate",
                "value": "docDate",
                "type": "D"
            },
            {
                "name": "calledByContact",
                "value": "calledByContactName",
                "type": "S"
            },
            {
                "name": "facilitatorContact",
                "value": "facilitatorContactName",
                "type": "S"
            },
            {
                "name": "calledByCompany",
                "value": "calledByCompanyName",
                "type": "S"
            },
            {
                "name": "facilitatorCompany",
                "value": "facilitatorContactName",
                "type": "S"
            },
            {
                "name": "noteTakerCompany",
                "value": "noteTakerCompanyName",
                "type": "S"
            },
            {
                "name": "noteTakerContact",
                "value": "noteTakerContactName",
                "type": "S"
            },
            {
                "name": "projectName",
                "value": "projectName",
                "type": "S"
            }
        ],
        "columnsItems": [
            "arrange",
            "description",
            "decisions",
            "action"
        ],
        "friendlyNames": [
            "numberAbb",
            "description",
            "decisions",
            "action"
        ]
    },
    "33": {
        "fields": [
            {
                "name": "subject",
                "value": "subject",
                "type": "S"
            },
            {
                "name": "handouts",
                "value": "handOuts",
                "type": "S"
            },
            {
                "name": "status",
                "value": "statusName",
                "type": "S"
            },
            {
                "name": "refDoc",
                "value": "refDoc",
                "type": "S"
            },
            {
                "name": "docDate",
                "value": "docDate",
                "type": "D"
            },
            {
                "name": "calledByContact",
                "value": "calledByContactName",
                "type": "S"
            },
            {
                "name": "facilitatorContact",
                "value": "facilitatorContactName",
                "type": "S"
            },
            {
                "name": "calledByCompany",
                "value": "calledByCompanyName",
                "type": "S"
            },
            {
                "name": "facilitatorCompany",
                "value": "facilitatorContactName",
                "type": "S"
            },
            {
                "name": "noteTakerCompany",
                "value": "noteTakerCompanyName",
                "type": "S"
            },
            {
                "name": "noteTakerContact",
                "value": "noteTakerContactName",
                "type": "S"
            },
            {
                "name": "projectName",
                "value": "projectName",
                "type": "S"
            }
        ],
        "columnsItems": [
            "description",
            "calledByCompany",
            "calledByContact",
            "decisions",
            "action"
        ],
        "friendlyNames": [
            "description",
            "calledByCompany",
            "calledByContact",
            "decisions",
            "action"
        ]
    },
    "29": {
        "fields": [
            {
                "name": "subject",
                "value": "subject",
                "type": "S"
            },
            {
                "name": "status",
                "value": "statusName",
                "type": "S"
            },
            {
                "name": "docDate",
                "value": "docDate",
                "type": "D"
            },
            {
                "name": "refDoc",
                "value": "refDoc",
                "type": "S"
            },
            {
                "name": "enteredBy",
                "value": "enteredby",
                "type": "S"
            },
            {
                "name": "callTime",
                "value": "callTime",
                "type": "S"
            },
            {
                "name": "fromCompany",
                "value": "fromCompanyName",
                "type": "S"
            },
            {
                "name": "fromContact",
                "value": "fromContactName",
                "type": "S"
            },
            {
                "name": "toCompany",
                "value": "toCompanyName",
                "type": "S"
            },
            {
                "name": "attention",
                "value": "toContactName",
                "type": "S"
            },
            {
                "name": "projectName",
                "value": "projectName",
                "type": "S"
            }
        ],
        "columnsItems": [],
        "friendlyNames": []
    },
    "20": {
        "fields": [
            {
                "name": "subject",
                "value": "subject",
                "type": "S"
            },
            {
                "name": "status",
                "value": "statusName",
                "type": "S"
            },
            {
                "name": "reportType",
                "value": "reportTypeName",
                "type": "S"
            },
            {
                "name": "docDate",
                "value": "docDate",
                "type": "D"
            },
            {
                "name": "refDoc",
                "value": "refDoc",
                "type": "S"
            },
            {
                "name": "fromCompany",
                "value": "fromCompanyName",
                "type": "S"
            },
            {
                "name": "fromContact",
                "value": "fromContactName",
                "type": "S"
            },
            {
                "name": "toCompany",
                "value": "toCompanyName",
                "type": "S"
            },
            {
                "name": "attention",
                "value": "toContactName",
                "type": "S"
            },
            {
                "name": "projectName",
                "value": "projectName",
                "type": "S"
            }
        ],
        "columnsItems": [],
        "friendlyNames": []
    },
    "21": {
        "fields": [
            {
                "name": "subject",
                "value": "subject",
                "type": "S"
            },
            {
                "name": "status",
                "value": "statusName",
                "type": "S"
            },
            {
                "name": "docDate",
                "value": "docDate",
                "type": "D"
            },
            {
                "name": "arrange",
                "value": "arrange",
                "type": "S"
            },
            {
                "name": "refDoc",
                "value": "refDoc",
                "type": "S"
            },
            {
                "name": "fromCompany",
                "value": "fromCompanyName",
                "type": "S"
            },
            {
                "name": "fromContact",
                "value": "fromContactName",
                "type": "S"
            },
            {
                "name": "toCompany",
                "value": "toCompanyName",
                "type": "S"
            },
            {
                "name": "attention",
                "value": "toContactName",
                "type": "S"
            },
            {
                "name": "projectName",
                "value": "projectName",
                "type": "S"
            }
        ],
        "columnsItems": [],
        "friendlyNames": []
    },
    "23": {
        "fields": [
            {
                "name": "subject",
                "value": "subject",
                "type": "S"
            },
            {
                "name": "status",
                "value": "statusName",
                "type": "S"
            },
            {
                "name": "refDoc",
                "value": "refDoc",
                "type": "S"
            },
            {
                "name": "docDate",
                "value": "docDate",
                "type": "D"
            },
            {
                "name": "requiredDate",
                "value": "requiredDate",
                "type": "D"
            },
            {
                "name": "discipline",
                "value": "discipline",
                "type": "S"
            },
            {
                "name": "location",
                "value": "location",
                "type": "S"
            },
            {
                "name": "area",
                "value": "area",
                "type": "S"
            },
            {
                "name": "Building",
                "value": "building",
                "type": "S"
            },
            {
                "name": "apartmentNumber",
                "value": "apartment",
                "type": "S"
            },
            {
                "name": "fromCompany",
                "value": "fromCompanyName",
                "type": "S"
            },
            {
                "name": "fromContact",
                "value": "fromContactName",
                "type": "S"
            },
            {
                "name": "toCompany",
                "value": "toCompanyName",
                "type": "S"
            },
            {
                "name": "attention",
                "value": "toContactName",
                "type": "S"
            },
            {
                "name": "message",
                "value": "rfi",
                "type": "S"
            },
            {
                "name": "answer",
                "value": "answer",
                "type": "S"
            },
            {
                "name": "projectName",
                "value": "projectName",
                "type": "S"
            }
        ],
        "columnsItems": [],
        "friendlyNames": []
    },
    "99": {
        "fields": [
            {
                "name": "subject",
                "value": "subject",
                "type": "S"
            },
            {
                "name": "status",
                "value": "statusName",
                "type": "S"
            },
            {
                "name": "docDate",
                "value": "docDate",
                "type": "D"
            }
        ],
        "columnsItems": [
            "arrange",
            "companyName",
            "contactName"
        ],
        "friendlyNames": [
            "numberAbb",
            "CompanyName",
            "ContactName"
        ]
    },
    "103": {
        "fields": [
            {
                "name": "subject",
                "value": "subject",
                "type": "S"
            },
            {
                "name": "docDate",
                "value": "docDate",
                "type": "D"
            },
            {
                "name": "refNo",
                "value": "refDoc",
                "type": "S"
            },
            {
                "name": "resultDate",
                "value": "resultDate",
                "type": "D"
            },
            {
                "name": "fromContact",
                "value": "fromContactName",
                "type": "S"
            },
            {
                "name": "attention",
                "value": "toContactName",
                "type": "S"
            },
            {
                "name": "actionByContact",
                "value": "bicContactName",
                "type": "S"
            },
            {
                "name": "discipline",
                "value": "discipline",
                "type": "S"
            },
            {
                "name": "reasonForIssue",
                "value": "reasonForIssueName",
                "type": "S"
            },
            {
                "name": "fileNumber",
                "value": "fileNumberName",
                "type": "S"
            },
            {
                "name": "Building",
                "value": "buildingNoName",
                "type": "S"
            },
            {
                "name": "comment",
                "value": "cycleComment",
                "type": "S"
            },
            {
                "name": "progressPercent",
                "value": "cycleProgressPercent",
                "type": "S"
            },
            {
                "name": "status",
                "value": "statusName",
                "type": "S"
            },
            {
                "name": "numberAbb",
                "value": "arrange",
                "type": "S"
            },
            {
                "name": "requiredDate",
                "value": "requiredDate",
                "type": "D"
            },
            {
                "name": "fromCompany",
                "value": "fromCompanyName",
                "type": "S"
            },
            {
                "name": "toCompany",
                "value": "toCompanyName",
                "type": "S"
            },
            {
                "name": "actionByCompany",
                "value": "bicCompanyName",
                "type": "S"
            },
            {
                "name": "contractPo",
                "value": "orderType ",
                "type": "S"
            },
            {
                "name": "specsSection",
                "value": "specsSectionName",
                "type": "S"
            },
            {
                "name": "revisionNo",
                "value": "revisions",
                "type": "S"
            },
            {
                "name": "area",
                "value": "areaName",
                "type": "S"
            },
            {
                "name": "apartmentNumber",
                "value": "apartmentNoName",
                "type": "S"
            },
            {
                "name": "CycleDetails",
                "value": "cycleComment",
                "type": "S"
            },
            {
                "name": "cycleSubject",
                "value": "cycleSubject",
                "type": "S"
            },
            {
                "name": "status",
                "value": "cycleStatusName",
                "type": "S"
            },
            {
                "name": "approvalStatus",
                "value": "cycleApprovalStatusName",
                "type": "S"
            },
            {
                "name": "projectName",
                "value": "projectName",
                "type": "S"
            },
            {
                "name": "docDate",
                "value": "cycleDocDate",
                "type": "S"
            }
        ],
        "columnsItems": [
            "subject",
            "docTypeName",
            "docDate"
        ],
        "friendlyNames": [
            "subject",
            "docType",
            "docDate"
        ]
    },
    "64": {
        "fields": [
            {
                "name": "subject",
                "value": "subject",
                "type": "S"
            },
           
            {
                "name": "status",
                "value": "statusName",
                "type": "S"
            },
            {
                "name": "docDate",
                "value": "documentDate",
                "type": "D"
            },
            {
                "name": "fromCompany",
                "value": "companyName",
                "type": "S"
            },
            {
                "name": "disciplineName",
                "value": "disciplineName",
                "type": "S"
            },
            {
                "name": "projectName",
                "value": "projectName",
                "type": "S"
            }
        ],
        "columnsItems": [
            "arrange",
            "boqType",
            "boqSubType",
            "itemCode",
            "description",
            "quantity",
            "revisedQuantity",
            "unit",
            "unitPrice",
            "total",
            "resourceCode"
        ],
        "friendlyNames": [
            "arrange",
            "boqType",
            "boqSubType",
            "itemCode",
            "description",
            "quantity",
            "revQuantity",
            "unit",
            "unitPrice",
            "total",
            "resourceCode"
        ]
    },
    "65": {
        "fields": [
            {
                "name": "subject",
                "value": "subject",
                "type": "S"
            },
            {
                "name": "status",
                "value": "statusName",
                "type": "S"
            },
            {
                "name": "docDate",
                "value": "docDate",
                "type": "D"
            },
            {
                "name": "arrange",
                "value": "arrange",
                "type": "S"
            },
            {
                "name": "CompanyName",
                "value": "companyName",
                "type": "S"
            },
            {
                "name": "contract",
                "value": "contractSubject",
                "type": "S"
            },
            {
                "name": "description",
                "value": "description",
                "type": "S"
            },
            {
                "name": "timeExtension",
                "value": "timeExtensionRequired",
                "type": "S"
            },
            {
                "name": "overHead",
                "value": "overHead",
                "type": "S"
            },
            {
                "name": "profit",
                "value": "profit",
                "type": "S"
            },
            {
                "name": "cvr",
                "value": "cvrName",
                "type": "S"
            },
            {
                "name": "approvalStatus",
                "value": "approvalStatusTitle",
                "type": "S"
            },
            {
                "name": "isLumpSum",
                "value": "lampSumStatus",
                "type": "S"
            },
            {
                "name": "lumpSum",
                "value": "lumpSumAmount",
                "type": "S"
            },
            {
                "name": "subContractor",
                "value": "subcontractorAmount",
                "type": "S"
            },
            {
                "name": "projectName",
                "value": "projectName",
                "type": "S"
            }
        ],
        "columnsItems": [
            "arrange",
            "description",
            "quantity",
            "unit",
            "unitPrice",
            "total",
            "days",
            "resourceCode"
        ],
        "friendlyNames": [
            "numberAbb",
            "description",
            "quantity",
            "unit",
            "unitPrice",
            "total",
            "days",
            "resourceCode"
        ]
    },
    "108": {
        "fields": [
            {
                "name": "subject",
                "value": "subject",
                "type": "S"
            },
            {
                "name": "description",
                "value": "description",
                "type": "S"
            },
            {
                "name": "status",
                "value": "statusName",
                "type": "S"
            },
            {
                "name": "refDoc",
                "value": "refDoc",
                "type": "S"
            },
            {
                "name": "docDate",
                "value": "docDate",
                "type": "D"
            },
            {
                "name": "contract",
                "value": "contractName",
                "type": "S"
            },
            {
                "name": "fromCompany",
                "value": "fromCompanyName",
                "type": "S"
            },
            {
                "name": "fromContact",
                "value": "fromContactName",
                "type": "S"
            },
            {
                "name": "toCompany",
                "value": "toCompanyName",
                "type": "S"
            },
            {
                "name": "ToContact",
                "value": "toContactName",
                "type": "S"
            },
            {
                "name": "projectName",
                "value": "projectName",
                "type": "S"
            }
        ],
        "columnsItems": [],
        "friendlyNames": []
    },
    "66": {
        "fields": [
            {
                "name": "subject",
                "value": "subject",
                "type": "S"
            },
            {
                "name": "status",
                "value": "statusName",
                "type": "S"
            },
            {
                "name": "docDate",
                "value": "docDate",
                "type": "D"
            },
            {
                "name": "arrange",
                "value": "arrange",
                "type": "S"
            },
            {
                "name": "pco",
                "value": "pcoSubject",
                "type": "S"
            },
            {
                "name": "contractSubject",
                "value": "contractSubject",
                "type": "S"
            },
            {
                "name": "dateApproved",
                "value": "dateApproved",
                "type": "D"
            },
            {
                "name": "timeExtension",
                "value": "timeExtensionRequired",
                "type": "S"
            },
            {
                "name": "executed",
                "value": "executed",
                "type": "S"
            },
            {
                "name": "total",
                "value": "total",
                "type": "S"
            },
            {
                "name": "projectName",
                "value": "projectName",
                "type": "S"
            }
        ],
        "columnsItems": [
            "arrange",
            "description",
            "quantity",
            "unitPrice",
            "resourceCode",
            "itemCode",
            "boqType",
            "boqSubType",
            "boqTypeChild"
        ],
        "friendlyNames": [
            "arrange",
            "description",
            "quantity",
            "unitPrice",
            "resourceCode",
            "itemCode",
            "boqType",
            "boqSubType",
            "boqTypeChild"
        ]
    },
    "18": {
        "fields": [
            {
                "name": "subject",
                "value": "subject",
                "type": "S"
            },
            {
                "name": "docDate",
                "value": "docDate",
                "type": "D"
            },
            {
                "name": "status",
                "value": "statusName",
                "type": "S"
            },
            {
                "name": "openDate",
                "value": "openDate",
                "type": ""
            },
            {
                "name": "CompanyName",
                "value": "companyName",
                "type": "S"
            },
            {
                "name": "disciplineTitle",
                "value": "disciplineTitle",
                "type": "S"
            },
            {
                "name": "projectName",
                "value": "projectName",
                "type": "S"
            }
        ],
        "columnsItems": [],
        "friendlyNames": []
    },
    "106": {
        "fields": [
            {
                "name": "subject",
                "value": "subject",
                "type": "S"
            },
            {
                "name": "refDoc",
                "value": "refDoc",
                "type": "S"
            },
            {
                "name": "status",
                "value": "statusName",
                "type": "S"
            },
            {
                "name": "docDate",
                "value": "docDate",
                "type": "D"
            },
            {
                "name": "approvalStatus",
                "value": "approvalStatusName",
                "type": "S"
            },
            {
                "name": "contractSubject",
                "value": "contractName",
                "type": "S"
            },
            {
                "name": "total",
                "value": "total",
                "type": "S"
            },
            {
                "name": "area",
                "value": "areaName",
                "type": "S"
            },
            {
                "name": "location",
                "value": "location",
                "type": "S"
            },
            {
                "name": "Building",
                "value": "building",
                "type": "S"
            },
            {
                "name": "apartmentNumber",
                "value": "apartmentNumber",
                "type": "S"
            },
            {
                "name": "fromCompany",
                "value": "fromCompanyName",
                "type": "S"
            },
            {
                "name": "fromContact",
                "value": "fromContactName",
                "type": "S"
            },
            {
                "name": "toCompany",
                "value": "toCompanyName",
                "type": "S"
            },
            {
                "name": "ToContact",
                "value": "toContactName",
                "type": "S"
            },
            {
                "name": "answer",
                "value": "answer",
                "type": "S"
            },
            {
                "name": "projectName",
                "value": "projectName",
                "type": "S"
            }
        ],
        "columnsItems": [],
        "friendlyNames": []
    },
    "107": {
        "fields": [
            {
                "name": "subject",
                "value": "subject",
                "type": "S"
            },
            {
                "name": "arrange",
                "value": "arrange",
                "type": "S"
            },
            {
                "name": "refDoc",
                "value": "refDoc",
                "type": "S"
            },
            {
                "name": "status",
                "value": "statusName",
                "type": "S"
            },
            {
                "name": "docDate",
                "value": "docDate",
                "type": "D"
            },
            {
                "name": "approvalStatus",
                "value": "approvalStatusName",
                "type": "S"
            },
            {
                "name": "contractSubject",
                "value": "contractName",
                "type": "S"
            },
            {
                "name": "total",
                "value": "total",
                "type": "S"
            },
            {
                "name": "area",
                "value": "areaName",
                "type": "S"
            },
            {
                "name": "location",
                "value": "location",
                "type": "S"
            },
            {
                "name": "Building",
                "value": "building",
                "type": "S"
            },
            {
                "name": "apartmentNumber",
                "value": "apartmentNumber",
                "type": "S"
            },
            {
                "name": "fromCompany",
                "value": "fromCompanyName",
                "type": "S"
            },
            {
                "name": "fromContact",
                "value": "fromContactName",
                "type": "S"
            },
            {
                "name": "toCompany",
                "value": "toCompanyName",
                "type": "S"
            },
            {
                "name": "ToContact",
                "value": "toContactName",
                "type": "S"
            },
            {
                "name": "answer",
                "value": "answer",
                "type": "S"
            },
            {
                "name": "projectName",
                "value": "projectName",
                "type": "S"
            }
        ],
        "columnsItems": [],
        "friendlyNames": []
    },
    "2": {
        "fields": [
            {
                "name": "subject",
                "value": "subject",
                "type": "S"
            },
            {
                "name": "arrange",
                "value": "arrange",
                "type": "S"
            },
            {
                "name": "docDate",
                "value": "docDate",
                "type": "D"
            },
            {
                "name": "description",
                "value": "description",
                "type": "S"
            },
            {
                "name": "picDate",
                "value": "picDate",
                "type": "D"
            },
            {
                "name": "fromCompany",
                "value": "fromCompanyName",
                "type": "S"
            },
            {
                "name": "fromContact",
                "value": "fromContactName",
                "type": "S"
            }
        ],
        "columnsItems": [],
        "friendlyNames": []
    },
    "90": {
        "fields": [
            {
                "name": "subject",
                "value": "subject",
                "type": "S"
            },
            {
                "name": "status",
                "value": "statusName",
                "type": "S"
            },
            {
                "name": "docDate",
                "value": "docDate",
                "type": "D"
            },
            {
                "name": "requiredDateLog",
                "value": "requiredDate",
                "type": "D"
            },
            {
                "name": "fromCompany",
                "value": "fromCompanyName",
                "type": "S"
            },
            {
                "name": "fromContact",
                "value": "fromContactName",
                "type": "S"
            },
            {
                "name": "toCompany",
                "value": "toCompanyName",
                "type": "S"
            },
            {
                "name": "ToContact",
                "value": "toContactName",
                "type": "S"
            },
            {
                "name": "projectName",
                "value": "projectName",
                "type": "S"
            },
            {
                "name": "contractPo",
                "value": "orderType",
                "type": "S"
            },
            {
                "name": "details",
                "value": "message",
                "type": "S"
            },
            {
                "name": "receivedFor",
                "value": "receivedFor",
                "type": "S"
            }
        ],
        "columnsItems": [],
        "friendlyNames": []
    },
    "42": {
        "fields": [
            {
                "name": "subject",
                "value": "subject",
                "type": "S"
            },
            {
                "name": "status",
                "value": "statusName",
                "type": "S"
            },
            {
                "name": "forwardToDate",
                "value": "forwardToDate",
                "type": "D"
            },
            {
                "name": "arrange",
                "value": "arrange",
                "type": "S"
            },
            {
                "name": "area",
                "value": "area",
                "type": "S"
            },
            {
                "name": "docDate",
                "value": "docDate",
                "type": "D"
            },
            {
                "name": "reasonForIssue",
                "value": "reasonForIssueName",
                "type": "S"
            },
            {
                "name": "discipline",
                "value": "disciplineName",
                "type": "S"
            },
            {
                "name": "refNo",
                "value": "refNo",
                "type": "S"
            },
            {
                "name": "location",
                "value": "location",
                "type": "S"
            },
            {
                "name": "Building",
                "value": "building",
                "type": "S"
            },
            {
                "name": "apartmentNumber",
                "value": "apartment",
                "type": "S"
            },
            {
                "name": "specsSection",
                "value": "specsSectionName",
                "type": "S"
            },
            {
                "name": "CompanyName",
                "value": "bicCompanyName",
                "type": "S"
            },
            {
                "name": "ContactName",
                "value": "bicContactName",
                "type": "S"
            },
            {
                "name": "submittalType",
                "value": "submittalType",
                "type": "S"
            },
            {
                "name": "CycleDetails",
                "value": " ",
                "type": "S"
            },
            {
                "name": "cycleSubject",
                "value": "subject",
                "type": "S"
            },
            {
                "name": "numberAbb",
                "value": "arrange",
                "type": "S"
            },
            {
                "name": "cycleDate",
                "value": "docDate",
                "type": "D"
            },
            {
                "name": "approvalStatus",
                "value": "approvalStatusName",
                "type": "S"
            },
            {
                "name": "status",
                "value": "statusName",
                "type": "S"
            }
        ],
        "columnsItems": [
            "arrange",
            "subject",
            "docDate",
            "statusName",
            "flowCompanyName",
            "flowContactName"
        ],
        "friendlyNames": [
            "numberAbb",
            "subject",
            "docDate",
            "status",
            "CompanyName",
            "ContactName"
        ]
    },
    "72": {
        "fields": [
            {
                "name": "subject",
                "value": "subject",
                "type": "S"
            },
            {
                "name": "status",
                "value": "statusName",
                "type": "S"
            },
            {
                "name": "docDate",
                "value": "docDate",
                "type": "D"
            },
            {
                "name": "arrange",
                "value": "arrange",
                "type": "S"
            },
            {
                "name": "comment",
                "value": "comment",
                "type": "S"
            },
            {
                "name": "purchaseOrder",
                "value": "purchaseOrderName",
                "type": "S"
            },
            {
                "name":"CompanyName",
                "value":"companyName",
                "type":"S"
            },
            {
                "name":"BOQCostCoding",
                "value":"boqName",
                "type":"S"
            },
            {
                "name":"costCodingTree",
                "value":"costCodingTreeName",
                "type":"S"
            },
            {
"name":"collectedStatus",
"value":"collectedStatus",
"type":"S"
            },
            {
                "name":"canceled",
                "value":"cancelled",
                "type":"S"
            },
            {
                "name":"transactionTypeName",
                "value":"transactionTypeTitle",
                "type":"S"
            },
            {
                "name":"approvalStatusName",
                "value":"approvalStatusName",
                "type":"S"
            }
        ],
        "columnsItems": [
            "arrange",
            "details",
            "resourceCode",
            "quantity",
            "unitPrice",
            "total",
            "days",
            "quantityComplete"
        ],
        "friendlyNames": [
            "number",
            "details",
            "resourceCode",
            "quantity",
            "unitPrice",
            "total",
            "days",
            "quantityComplete"
        ]
    },
    "114": {
        "fields": [
            {
                "name": "subject",
                "value": "subject",
                "type": "S"
            },
            {
                "name": "discipline",
                "value": "disciplineName",
                "type": "S"
            },
            {
                "name": "fileNumber",
                "value": "fileNumber",
                "type": "S"
            },
            {
                "name": "numberAbb",
                "value": "arrange",
                "type": "S"
            },
            {
                "name": "docDate",
                "value": "docDate",
                "type": "D"
            },
            {
                "name": "area",
                "value": "area",
                "type": "S"
            },
            {
                "name": "status",
                "value": "statusName",
                "type": "S"
            },
            {
                "name": "refDoc",
                "value": "refNo",
                "type": "S"
            },
            {
                "name": "reasonForIssue",
                "value": "reasonForIssueName",
                "type": "S"
            },
            {
                "name": "drawingNo",
                "value": "drawingNo",
                "type": "S"
            },
            {
                "name": "specsSection",
                "value": "specsSectionName",
                "type": "S"
            },
            {
                "name": "CompanyName",
                "value": "companyName",
                "type": "S"
            },
            {
                "name": "ContactName",
                "value": "bicContactName",
                "type": "S"
            }
        ],
        "columnsItems": [
            "subject",
            "docDate",
            "statusName",
            "flowCompanyName",
            "flowContactName",
            "progressPercent"
        ],
        "friendlyNames": [
            "subject",
            "docDate",
            "status",
            "CompanyName",
            "ContactName",
            "progressPercent"
        ]
    },
    "37": {
        "fields": [
            {
                "name": "subject",
                "value": "subject",
                "type": "S"
            },
            {
                "name": "discipline",
                "value": "disciplineName",
                "type": "S"
            },
            {
                "name": "fileNumber",
                "value": "fileNumber",
                "type": "S"
            },
            {
                "name": "numberAbb",
                "value": "arrange",
                "type": "S"
            },
            {
                "name": "docDate",
                "value": "docDate",
                "type": "D"
            },
            {
                "name": "area",
                "value": "area",
                "type": "S"
            },
            {
                "name": "status",
                "value": "statusName",
                "type": "S"
            },
            {
                "name": "refDoc",
                "value": "refNo",
                "type": "S"
            },
            {
                "name": "reasonForIssue",
                "value": "reasonForIssueName",
                "type": "S"
            },
            {
                "name": "drawingNo",
                "value": "drawingNo",
                "type": "S"
            },
            {
                "name": "specsSection",
                "value": "specsSectionName",
                "type": "S"
            },
            {
                "name": "CompanyName",
                "value": "companyName",
                "type": "S"
            },
            {
                "name": "ContactName",
                "value": "bicContactName",
                "type": "S"
            }
        ],
        "columnsItems": [
            "subject",
            "docDate",
            "statusName",
            "flowCompanyName",
            "flowContactName",
            "progressPercent"
        ],
        "friendlyNames": [
            "subject",
            "docDate",
            "status",
            "CompanyName",
            "ContactName",
            "progressPercent"
        ]
    },
    "39": {
        "fields": [
            {
                "name": "subject",
                "value": "subject",
                "type": "S"
            },
            {
                "name": "arrange",
                "value": "arrange",
                "type": "S"
            },
            {
                "name": "status",
                "value": "statusName",
                "type": "S"
            },
            {
                "name": "docDate",
                "value": "docDate",
                "type": "D"
            },
            {
                "name": "projectType",
                "value": "projectTypeId",
                "type": "S"
            },
            {
                "name": "projectName",
                "value": "projectName",
                "type": "S"
            }
        ],
        "columnsItems": [],
        "friendlyNames": []
    },
    "38": {
        "fields": [
            {
                "name": "subject",
                "value": "subject",
                "type": "S"
            },
            {
                "name": "progressPercent",
                "value": "progressPercent",
                "type": "S"
            },
            {
                "name": "docDate",
                "value": "docDate",
                "type": "D"
            },
            {
                "name": "discipline",
                "value": "disciplineName",
                "type": "S"
            },
            {
                "name": "fileNumber",
                "value": "fileNumberId",
                "type": "S"
            },
            {
                "name": "actionByCompany",
                "value": "bicCompanyName",
                "type": "S"
            },
            {
                "name": "area",
                "value": "area",
                "type": "S"
            },
            {
                "name": "status",
                "value": "statusName",
                "type": "S"
            },
            {
                "name": "reasonForIssue",
                "value": "reasonForIssueName",
                "type": "S"
            },
            {
                "name": "specsSection",
                "value": "specsSectionName",
                "type": "S"
            },
            {
                "name": "projectName",
                "value": "projectName",
                "type": "S"
            }
        ],
        "columnsItems": [
            "drawingName",
            "docDate",
            "status",
            "bicCompanyName",
            "bicContactName"
        ],
        "friendlyNames": [
            "subject",
            "docDate",
            "status",
            "actionByCompany",
            "actionByContact"
        ]
    },
    "89": {
        "fields": [
            {
                "name": "subject",
                "value": "subject",
                "type": "S"
            },
            {
                "name": "status",
                "value": "statusName",
                "type": "S"
            },
            {
                "name": "docDate",
                "value": "docDate",
                "type": "D"
            }
        ],
        "columnsItems": [
            "arrange",
            "companyName",
            "contactName"
        ],
        "friendlyNames": [
            "numberAbb",
            "CompanyName",
            "ContactName"
        ]
    },
    "16": {
        "fields": [
            {
                "name": "subject",
                "value": "subject",
                "type": "S"
            },
            {
                "name": "status",
                "value": "statusName",
                "type": "S"
            },
            {
                "name": "docDate",
                "value": "docDate",
                "type": "D"
            },
            {
                "name": "arrange",
                "value": "arrange",
                "type": "S"
            },
            {
                "name": "rejectionOption",
                "value": "rejectionOptionsName",
                "type": "S"
            },
            {
                "name": "nextWorkFlow",
                "value": "nextWorkFlowName",
                "type": "S"
            },
            {
                "name": "closeAfterApproval",
                "value": "closeAfterApprovalName",
                "type": "S"
            },
            {
                "name": "useSelection",
                "value": "useSelectionName",
                "type": "S"
            }
        ],
        "columnsItems": [
            "arrange",
            "companyName",
            "contactName",
            "description"
        ],
        "friendlyNames": [
            "numberAbb",
            "CompanyName",
            "ContactName",
            "description"
        ]
    },
    "9": {
        "fields": [
            {
                "name": "subject",
                "value": "subject",
                "type": "S"
            },
            {
                "name": "tax",
                "value": "tax",
                "type": "S"
            },
            {
                "name": "vat",
                "value": "vat",
                "type": "S"
            },
            {
                "name": "retainage",
                "value": "retainage",
                "type": "S"
            },
            {
                "name": "insurance",
                "value": "insurance",
                "type": "S"
            },
            {
                "name": "advancedPayment",
                "value": "advancedPayment",
                "type": "S"
            },
            {
                "name": "advancedPaymentAmount",
                "value": "advancedPaymentAmount",
                "type": "S"
            },
            {
                "name": "docDate",
                "value": "docDate",
                "type": "S"
            },
            {
                "name": "completionDate",
                "value": "completionDate",
                "type": "S"
            },
            {
                "name": "fromCompany",
                "value": "companyName",
                "type": "S"
            },
            {
                "name": "contractTo",
                "value": "toCompanyName",
                "type": "S"
            },
            {
                "name": "contractWithContact",
                "value": "toContactName",
                "type": "S"
            },
            {
                "name": "originalContractSum",
                "value": "originalContactSum",
                "type": "S"
            },
            {
                "name": "revisedContractSumToDate",
                "value": "revisedContractSum",
                "type": "S"
            },
            {
                "name": "actualExceuted",
                "value": "actualExceuted",
                "type": "S"
            },
            {
                "name": "balanceToFinish",
                "value": "balanceToFinish",
                "type": "S"
            },
            {
                "name": "changeOrderSum",
                "value": "approvedChangeOrder",
                "type": "S"
            }
            
        ],
        "columnsItems": [
            "details",
            "boqType",
            "boqTypeChild",
            "boqSubType",
            "originalQuantity",
            "quantity",
            "unit",
            "originalUnitPrice",
            "total",
            "resourceCode",
            "itemCode",
            "specsSectionName",
            "reviceQuantity"
        ],
        "friendlyNames": [
            "description",
            "boqType",
            "boqTypeChild",
            "boqSubType",
            "originalQuantity",
            "remainingQuantity",
            "unit",
            "unitPrice",
            "total",
            "resourceCode",
            "itemCode",
            "specsSection",
            "revQuantity"
        ]
    },
    "88": {
        "fields": [
            {
                "name": "subject",
                "value": "subject",
                "type": "S"
            },
            {
                "name": "status",
                "value": "statusName",
                "type": "S"
            },
            {
                "name": "docDate",
                "value": "docDate",
                "type": "D"
            },
            {
                "name": "arrange",
                "value": "arrange",
                "type": "S"
            },
            {
                "name": "requiredDateLog",
                "value": "requiredDate",
                "type": "D"
            },
            {
                "name": "CompanyName",
                "value": "companyName",
                "type": "S"
            },
            {
                "name": "area",
                "value": "area",
                "type": "S"
            },
            {
                "name": "location",
                "value": "location",
                "type": "S"
            },
            {
                "name": "disciplineTitle",
                "value": "disciplineName",
                "type": "S"
            },
            {
                "name": "revQuantity",
                "value": "quantityRevisedStatus",
                "type": "S"
            },
            {
                "name": "buildingNumber",
                "value": "buildingNo",
                "type": "S"
            },
            {
                "name": "apartmentNumber",
                "value": "apartmentNo",
                "type": "S"
            },
            {
                "name": "projectName",
                "value": "projectName",
                "type": "S"
            }
        ],
        "columnsItems": [
            "arrange",
            "details",
            "quantity",
            "unit",
            "days",
            "resourceCode",
            "stock"
        ],
        "friendlyNames": [
            "numberAbb",
            "description",
            "quantity",
            "unit",
            "days",
            "resourceCode",
            "stock"
        ]
    },
    "97": {
        "fields": [
            {
                "name": "subject",
                "value": "subject",
                "type": "S"
            },
            {
                "name": "status",
                "value": "statusName",
                "type": "S"
            },
            {
                "name": "docDate",
                "value": "docDate",
                "type": "D"
            },
            {
                "name": "startDate",
                "value": "startDate",
                "type": "D"
            },
            {
                "name": "finishDate",
                "value": "endDate",
                "type": "D"
            },
            {
                "name": "consultatnt",
                "value": "companyName",
                "type": "S"
            },
            {
                "name": "weekNumber",
                "value": "weekNumber",
                "type": "S"
            },
            {
                "name": "projectManager",
                "value": "companyNameManager",
                "type": "S"
            },
            {
                "name": "projectContact",
                "value": "contactNameManager",
                "type": "S"
            },
            {
                "name": "siteCompany",
                "value": "contactNameEngineer",
                "type": "S"
            },
            {
                "name": "siteEngineer",
                "value": "companyNameEngineer",
                "type": "S"
            },
            {
                "name": "projectName",
                "value": "projectName",
                "type": "S"
            }
        ],
        "columnsItems": [],
        "friendlyNames": []
    },
    "60": {
        "fields": [
            {
                "name": "subject",
                "value": "subject",
                "type": "S"
            },
            {
                "name": "status",
                "value": "statusName",
                "type": "S"
            },
            {
                "name": "docDate",
                "value": "docDate",
                "type": "D"
            },
            {
                "name": "arrange",
                "value": "arrange",
                "type": "S"
            },
            {
                "name": "CompanyName",
                "value": "companyName",
                "type": "S"
            },
            {
                "name": "projectName",
                "value": "projectName",
                "type": "S"
            }
        ],
        "columnsItems": [],
        "friendlyNames": []
    },
    "71": {
        "fields": [
            {
                "name": "projectName",
                "value": "projectName",
                "type": "S"
            },
            {
                "name": "subject",
                "value": "subject",
                "type": "S"
            },
            {
                "name": "status",
                "value": "statusName",
                "type": "S"
            },
            {
                "name": "docDate",
                "value": "documentDate",
                "type": "D"
            },
            {
                "name": "contract",
                "value": "contractName",
                "type": "S"
            },
            {
                "name": "originalContractSum",
                "value": "originalContractSum",
                "type": "S"
            },
            {
                "name": "contractExecutedToDate",
                "value": "contractExecutedToDate",
                "type": "S"
            },
            {
                "name": "advancedPayment",
                "value": "advancePaymentAmount",
                "type": "S"
            },
            {
                "name": "actualPayment",
                "value": "actualPayment",
                "type": "S"
            }
        ],
        "columnsItems": [
            "description",
            "prevoiuse",
            "currentValue",
            "total",
            "contractorPrevoiuse",
            "contractorCurrentValue",
            "contractorTotal"
        ],
        "friendlyNames": [
            "workDescription",
            "previous",
            "current",
            "total",
            "previousContractor",
            "currentContractor",
            "totalContractor"
        ]
    },
    "77": {
        "fields": [
            {
                "name": "subject",
                "value": "subject",
                "type": "S"
            },
            {
                "name": "status",
                "value": "statusName",
                "type": "S"
            },
            {
                "name": "docDate",
                "value": "documentDate",
                "type": "D"
            },
            {
                "name": "arrange",
                "value": "arrange",
                "type": "S"
            },
            {
                "name": "refDoc",
                "value": "refDoc",
                "type": "S"
            },
            {
                "name": "fromCompany",
                "value": "fromCompanyName",
                "type": "S"
            },
            {
                "name": "fromContact",
                "value": "fromContactName",
                "type": "S"
            },
            {
                "name": "toCompany",
                "value": "toCompanyName",
                "type": "S"
            },
            {
                "name": "attention",
                "value": "toContactName",
                "type": "S"
            },
            {
                "name": "projectName",
                "value": "projectName ",
                "type": "S"
            }
        ],
        "columnsItems": [],
        "friendlyNames": []
    },
    "98": {
        "fields": [
            {
                "name": "subject",
                "value": "subject",
                "type": "S"
            },
            {
                "name": "status",
                "value": "statusName",
                "type": "S"
            },
            {
                "name": "docDate",
                "value": "documentDate",
                "type": "D"
            },
            {
                "name": "fromCompany",
                "value": "companyName",
                "type": "S"
            },
            {
                "name": "disciplineName",
                "value": "disciplineName",
                "type": "S"
            },
            {
                "name": "projectName",
                "value": "projectName",
                "type": "S"
            }
        ],
        "columnsItems": [
            "arrange",
            "details",
            "quantity",
            "revQuantity",
            "unit",
            "unitPrice",
            "total",
            "resourceCode"
        ],
        "friendlyNames": [
            "arrange",
            "details",
            "quantity",
            "revQuantity",
            "unit",
            "unitPrice",
            "total",
            "resourceCode"
        ]
    },
    "120": {
        "fields": [
            {
                "name": "clientName",
                "value": "clientName",
                "type": "S"
            },
            {
                "name": "contractAmount",
                "value": "contractAmount",
                "type": "S"
            },
            {
                "name": "projectName",
                "value": "projectName",
                "type": "S"
            },
            {
                "name": "requestSubject",
                "value": "requestSubject",
                "type": "S"
            },
            {
                "name": "percentageOfWorkDone",
                "value": "percentageOfWorkDone",
                "type": "S"
            },
            {
                "name": "contractorName",
                "value": "contractName",
                "type": "S"
            },
            {
                "name": "contractorRefNumber",
                "value": "contractRefNumber",
                "type": "S"
            },
            {
                "name": "phdApproval",
                "value": "creationDate",
                "type": "D"
            },
            {
                "name": "invoiceCutOff",
                "value": "invoiceCut",
                "type": "D"
            },
            {
                "name": "invoiceSubmissionDate",
                "value": "invoiceSubmissionDate",
                "type": "D"
            },
            {
                "name": "consultantApproalDate",
                "value": "consultantApproalDate",
                "type": "D"
            }
        ],
        "columnsItems": [
            "description",
            "contractAmount",
            "contractorPrevoiuse",
            "contractorCurrentValue",
            "contractorTotal",
            "prevoiuse",
            "currentValue",
            "total",
            "totalDeduction",
            "remarks"
        ],
        "friendlyNames": [
            "description",
            "contractAmount",
            "contractorPrevoiuse",
            "contractorCurrentValue",
            "contractorTotal",
            "prevoiuse",
            "currentValue",
            "total",
            "totalDeduction",
            "remarks"
        ]
    },
    "17": {
        "fields": [
            {
                "name": "subject",
                "value": "subject",
                "type": "S"
            },
            {
                "name": "statusName",
                "value": "statusName",
                "type": "S"
            },
            {
                "name": "projectName",
                "value": "projectName",
                "type": "S"
            },
            {
                "name": "docDate",
                "value": "docDate",
                "type": "D"
            },
            {
                "name": "arrange",
                "value": "arrange",
                "type": "S"
            },
            {
                "name": "fromCompany",
                "value": "fromCompanyName",
                "type": "S"
            },
            {
                "name": "fromContact",
                "value": "fromContactName",
                "type": "S"
            },
            {
                "name": "toCompany",
                "value": "bicCompanyName",
                "type": "S"
            },
            {
                "name": "toContactName",
                "value": "bicContactName",
                "type": "S"
            },
            {
                "name": "startDate",
                "value": "startDate",
                "type": "D"
            },
            {
                "name": "finishDate",
                "value": "finishDate",
                "type": "D"
            },
            {
                "name": "estimatedTime",
                "value": "estimatedTime",
                "type": "S"
            },
            {
                "name": "priority",
                "value": "priorityName",
                "type": "S"
            },
            {
                "name": "description",
                "value": "description",
                "type": "S"
            },
            {
                "name": "taskActivity",
                "value": "suspendedText",
                "type": "S"
            }
        ],
        "friendlyNames": []
    },
    "121": {
        "fields": [
            {
                "name": "projectName",
                "value": "projectName",
                "type": "S"
            },
            {
                "name": "paymentRequistion",
                "value": "paymentRequistion",
                "type": "S"
            }
        ],
        "columnsItems": [
            "arrange",
            "boqType",
            "secondLevel",
            "itemCode",
            "subject",
            "unit",
            "unitPrice",
            "quantity",
            "revisedQuantity",
            "earnedQuantity",
            "quantityComplete",
            "paymentPercent",
            "wasAdded",
            "totalExcutedPayment",
            "lastComment",
            "itemStatus"
        ],
        "friendlyNames": [
            "no",
            "boqType",
            "boqTypeChild",
            "itemCode",
            "description",
            "unit",
            "unitPrice",
            "boqQuanty",
            "approvedQuantity",
            "earnedQuantity",
            "quantityComplete",
            "paymentPercent",
            "status",
            "totalAmount",
            "comment",
            "itemStatus"
        ]
    },
    "49": {
        "fields": [
            {
                "name": "subject",
                "value": "subject",
                "type": "S"
            },
            {
                "name": "status",
                "value": "statusName",
                "type": "S"
            },
            {
                "name": "docDate",
                "value": "docDate",
                "type": "D"
            },
            {
                "name": "arrange",
                "value": "arrange",
                "type": "S"
            },
            {
                "name": "specsSection",
                "value": "specsSectionName",
                "type": "S"
            },
            {
                "name": "materialDeliveryType",
                "value": "materialDeliveryTypeName",
                "type": "S"
            }
        ],
        "columnsItems": [
            "arrange",
            "description",
            "quantity",
            "unitPrice",
            "approvedQuantity",
            "rejectedQuantity",
            "pendingQuantity",
            "remaining",
            "receivedDate",
            "nextDeliveryDate",
            "resourceCode",
            "remarks"
        ],
        "friendlyNames": [
            "arrange",
            "description",
            "quantity",
            "unitPrice",
            "approvedQuantity",
            "rejectedQuantity",
            "pendingQuantity",
            "remainingQuantity",
            "recievedDate",
            "nextDate",
            "resourceCode",
            "remarks"
        ]
    }
}